django_dumpdata_one/__init__.py
django_dumpdata_one/models.py
django_dumpdata_one/management/__init__.py
django_dumpdata_one/management/commands/__init__.py
django_dumpdata_one/management/commands/dumpdata_one.py
django_dumpdata_one-0.8.6.dist-info/LICENSE
django_dumpdata_one-0.8.6.dist-info/METADATA
django_dumpdata_one-0.8.6.dist-info/WHEEL
django_dumpdata_one-0.8.6.dist-info/top_level.txt
django_dumpdata_one-0.8.6.dist-info/RECORD
